sesh/__init__.py
sesh/cli.py
sesh/credentials.py
aws_sesh-0.0.1.dist-info/LICENSE
aws_sesh-0.0.1.dist-info/METADATA
aws_sesh-0.0.1.dist-info/WHEEL
aws_sesh-0.0.1.dist-info/entry_points.txt
aws_sesh-0.0.1.dist-info/top_level.txt
aws_sesh-0.0.1.dist-info/RECORD
