Metadata-Version: 2.1
Name: aws-sesh
Version: 0.0.1
Summary: AWS MFA session manager
Home-page: https://github.com/panchgonzalez/aws-sesh
Author: Francisco Gonzalez
Author-email: fg@panch.io
License: UNKNOWN
Platform: UNKNOWN
License-File: LICENSE
